Workbook

Sheet Revenue Distribution by Product
A3: Row Labels | B3: Sum of Revenue generated
A4: cosmetics | B4: 161521.27
A5: haircare | B5: 174455.42
A6: skincare | B6: 241628.17
A7: Grand Total | B7: 577604.86

Sheet Sales Volume by SKU
A3: Row Labels | B3: Sum of Number of products sold
A4: SKU0 | B4: 802
A5: SKU1 | B5: 736
A6: SKU10 | B6: 996
A7: SKU11 | B7: 960
A8: SKU12 | B8: 336
A9: SKU13 | B9: 249
A10: SKU14 | B10: 562
A11: SKU15 | B11: 469
A12: SKU16 | B12: 280
A13: SKU17 | B13: 126
A14: SKU18 | B14: 620
A15: SKU19 | B15: 187
... A104: Grand Total | B104: 46099

Sheet Average Price by Product Type
A3: Row Labels | B3: Average of Price
A4: cosmetics | B4: 57.361154
A5: haircare | B5: 46.014118
A6: skincare | B6: 47.2595
A7: Grand Total | B7: 49.4625

Sheet Impact of Price on Products Sol

Sheet Products Sold by Customer Demog
A3: Row Labels | B3: Sum of Number of products sold
A4: cosmetics | B4: 11757
A5: Female | B5: 4012
A6: Male | B6: 2304
A7: Non-binary | B7: 2607
A8: Unknown | B8: 2834
A9: haircare | B9: 13611
A10: Female | B10: 936
A11: Male | B11: 2292
A12: Non-binary | B12: 2820
A13: Unknown | B13: 7563
A14: skincare | B14: 20731
A15: Female | B15: 7853
... A19: Grand Total | B19: 46099

Sheet Inventory Turnover Analysis by 
A3: Row Labels | B3: Sum of inventory turnover per SKU
A4: SKU0 | B4: 16.78878
A5: SKU1 | B5: 15.407159
A6: SKU10 | B6: 20.849906
A7: SKU11 | B7: 20.096295
A8: SKU12 | B8: 7.0337032
A9: SKU13 | B9: 5.2124764
A10: SKU14 | B10: 11.764706
A11: SKU15 | B11: 9.8178773
A12: SKU16 | B12: 5.8614193
A13: SKU17 | B13: 2.6376387
A14: SKU18 | B14: 12.978857
A15: SKU19 | B15: 3.9145907
... A103: SKU99 | B103: 13.125393
A104: (blank)
A105: Grand Total | B105: 965.01989

Sheet Stock Levels by SKU
A3: Row Labels | B3: Sum of Stock levels
A4: SKU0 | B4: 58
A5: SKU1 | B5: 53
A6: SKU10 | B6: 51
A7: SKU11 | B7: 46
A8: SKU12 | B8: 100
A9: SKU13 | B9: 80
A10: SKU14 | B10: 54
A11: SKU15 | B11: 9
A12: SKU16 | B12: 2
A13: SKU17 | B13: 45
A14: SKU18 | B14: 10
A15: SKU19 | B15: 48
... A103: SKU99 | B103: 55
A104: (blank)
A105: Grand Total | B105: 4777

Sheet Revenue Distribution by Custome
A3: Row Labels | B3: Sum of Revenue generated
A4: Female | B4: 161514.49
A5: Male | B5: 126634.42
A6: Non-binary | B6: 116365.81
A7: Unknown | B7: 173090.14
A8: Grand Total | B8: 577604.86

Sheet Average Lead Time by Supplier
A3: Row Labels | B3: Average of Lead time
A4: Supplier 1 | B4: 14.777778
A5: Supplier 2 | B5: 18.545455
A6: Supplier 3 | B6: 20.133333
A7: Supplier 4 | B7: 15.222222
A8: Supplier 5 | B8: 18.055556
A9: Grand Total | B9: 17.08

Sheet Production Volume by Supplier
A3: Row Labels | B3: Sum of Production volumes
A4: Supplier 1 | B4: 13545
A5: Supplier 2 | B5: 14105
A6: Supplier 3 | B6: 7997
A7: Supplier 4 | B7: 11756
A8: Supplier 5 | B8: 9381
A9: Grand Total | B9: 56784

Sheet Costs by SKU
A3: Row Labels | B3: Sum of costs
A4: SKU0 | B4: 187.75
A5: SKU1 | B5: 503.07
A6: SKU10 | B6: 806.1
A7: SKU11 | B7: 126.72
A8: SKU12 | B8: 402.97
A9: SKU13 | B9: 547.24
A10: SKU14 | B10: 929.24
A11: SKU15 | B11: 127.86
A12: SKU16 | B12: 865.53
A13: SKU17 | B13: 670.93
A14: SKU18 | B14: 593.48
A15: SKU19 | B15: 477.31
... A103: SKU99 | B103: 210.74
A104: (blank)
A105: Grand Total | B105: 52924.57

Sheet Shipping Costs per Transportati
A3: Row Labels | B3: Average of Shipping costs
A4: Air | B4: 6.0176923
A5: Rail | B5: 5.4692857
A6: Road | B6: 5.5424138
A7: Sea | B7: 4.97
A8: Grand Total | B8: 5.5482

Sheet Impact of Route on Shipping Tim
A3: Row Labels | B3: Sum of Shipping times
A4: Route A | B4: 259
A5: Route B | B5: 211
A6: Route C | B6: 105
A7: Grand Total | B7: 575

Sheet Supplier Costs and Lead Time Ov
A3: Row Labels | B3: Sum of Shipping costs | C3: Sum of Manufacturing costs | D3: Sum of Lead times
A4: Supplier 1 | B4: 148.83 | C4: 1221.85 | D4: 453
A5: Supplier 2 | B5: 126.26 | C5: 915.68 | D5: 357
A6: Supplier 3 | B6: 71.84 | C6: 654.52 | D6: 215
A7: Supplier 4 | B7: 103.66 | C7: 1128.76 | D7: 306
A8: Supplier 5 | B8: 104.23 | C8: 805.83 | D8: 265
A9: Grand Total | B9: 554.82 | C9: 4726.64 | D9: 1596

Sheet supply_chain
A1: Product type | B1: SKU | C1: Price | D1: Availability | E1: Number of products sold | F1: Revenue generated | G1: Customer demographics | H1: Stock levels | I1: Lead times | J1: Order quantities | K1: Shipping times | L1: Shipping carriers | M1: Shipping costs | N1: Supplier name | O1: Location | P1: Lead time | Q1: Production volumes | R1: Manufacturing lead time | S1: Manufacturing costs | T1: Inspection results | U1: Defect rates | V1: Transportation modes | W1: Routes | X1: costs | Y1: inventory turnover per SKU | Z1: Excess inventory products | AA1: lowest cost per unit suppliers | AB1: manufacturing efficiency | AC1: heghest manufacturing cost per unit | AD1: total supply chain cost per SKU
A2: haircare | B2: SKU0 | C2: 69.81 | D2: 55 | E2: 802 | F2: 8662 | G2: Non-binary | H2: 58 | I2: 7 | J2: 96 | K2: 4 | L2: Carrier B | M2: 2.96 | N2: Supplier 3 | O2: Mumbai | P2: 29 | Q2: 215 | R2: 29 | S2: 46.28 | T2: Pending | U2: 0.23 | V2: Road | W2: Route B | X2: 187.75 | Y2: {=supply_chain_data[Number of products sold] / AVERAGE(supply_chain_data[Stock levels])} -> 16.78878 | Z2: {=IF(supply_chain_data[Stock levels] > supply_chain_data[Number of products sold], "overstock","normal")} -> normal | AA2: {=supply_chain_data[Production volumes] / (supply_chain_data[Shipping costs] + supply_chain_data[Manufacturing costs])} -> 4.3663688 | AB2: {=supply_chain_data[Production volumes] / supply_chain_data[Manufacturing lead time]} -> 7.4137931 | AC2: {=supply_chain_data[Production volumes] / supply_chain_data[Manufacturing costs]} -> 4.6456353 | AD2: {=supply_chain_data[Manufacturing costs] + supply_chain_data[Shipping costs] + supply_chain_data[costs]} -> 236.99
A3: skincare | B3: SKU1 | C3: 14.84 | D3: 95 | E3: 736 | F3: 7460.9 | G3: Female | H3: 53 | I3: 30 | J3: 37 | K3: 2 | L3: Carrier A | M3: 9.72 | N3: Supplier 3 | O3: Mumbai | P3: 23 | Q3: 517 | R3: 30 | S3: 33.62 | T3: Pending | U3: 4.85 | V3: Road | W3: Route B | X3: 503.07 | Y3: 15.407159 | Z3: normal | AA3: 11.928934 | AB3: 17.233333 | AC3: 15.377751 | AD3: 546.41
A4: haircare | B4: SKU2 | C4: 11.32 | D4: 34 | E4: 8 | F4: 9577.75 | G4: Unknown | H4: 1 | I4: 10 | J4: 88 | K4: 2 | L4: Carrier B | M4: 8.05 | N4: Supplier 1 | O4: Mumbai | P4: 12 | Q4: 971 | R4: 27 | S4: 30.69 | T4: Pending | U4: 4.58 | V4: Air | W4: Route C | X4: 141.92 | Y4: 0.16746912 | Z4: normal | AA4: 25.064533 | AB4: 35.962963 | AC4: 31.63897 | AD4: 180.66
A5: skincare | B5: SKU3 | C5: 61.16 | D5: 68 | E5: 83 | F5: 7766.84 | G5: Non-binary | H5: 23 | I5: 13 | J5: 59 | K5: 6 | L5: Carrier C | M5: 1.73 | N5: Supplier 5 | O5: Kolkata | P5: 24 | Q5: 937 | R5: 18 | S5: 35.62 | T5: Fail | U5: 4.75 | V5: Rail | W5: Route A | X5: 254.78 | Y5: 1.7374921 | Z5: normal | AA5: 25.087015 | AB5: 52.055556 | AC5: 26.305446 | AD5: 292.13
A6: skincare | B6: SKU4 | C6: 4.81 | D6: 26 | E6: 871 | F6: 2686.51 | G6: Non-binary | H6: 5 | I6: 3 | J6: 56 | K6: 8 | L6: Carrier A | M6: 3.89 | N6: Supplier 1 | O6: Delhi | P6: 5 | Q6: 414 | R6: 3 | S6: 92.07 | T6: Fail | U6: 3.15 | V6: Air | W6: Route A | X6: 923.44 | Y6: 18.233201 | Z6: normal | AA6: 4.3142976 | AB6: 138 | AC6: 4.4965787 | AD6: 1019.4
A7: haircare | B7: SKU5 | C7: 1.7 | D7: 87 | E7: 147 | F7: 2828.35 | G7: Non-binary | H7: 90 | I7: 27 | J7: 66 | K7: 3 | L7: Carrier B | M7: 4.44 | N7: Supplier 4 | O7: Bangalore | P7: 10 | Q7: 104 | R7: 17 | S7: 56.77 | T7: Fail | U7: 2.78 | V7: Road | W7: Route A | X7: 235.46 | Y7: 3.0772451 | Z7: normal | AA7: 1.6990688 | AB7: 6.1176471 | AC7: 1.8319535 | AD7: 296.67
A8: skincare | B8: SKU6 | C8: 4.08 | D8: 48 | E8: 65 | F8: 7823.48 | G8: Male | H8: 11 | I8: 15 | J8: 58 | K8: 8 | L8: Carrier C | M8: 3.88 | N8: Supplier 3 | O8: Kolkata | P8: 14 | Q8: 314 | R8: 24 | S8: 1.09 | T8: Pending | U8: 1 | V8: Sea | W8: Route A | X8: 134.37 | Y8: 1.3606866 | Z8: normal | AA8: 63.179074 | AB8: 13.083333 | AC8: 288.07339 | AD8: 139.34
A9: cosmetics | B9: SKU7 | C9: 42.96 | D9: 59 | E9: 426 | F9: 8496.1 | G9: Female | H9: 93 | I9: 17 | J9: 11 | K9: 1 | L9: Carrier B | M9: 2.35 | N9: Supplier 4 | O9: Bangalore | P9: 22 | Q9: 564 | R9: 1 | S9: 99.47 | T9: Fail | U9: 0.4 | V9: Road | W9: Route C | X9: 802.06 | Y9: 8.9177308 | Z9: normal | AA9: 5.5391868 | AB9: 564 | AC9: 5.6700513 | AD9: 903.88
A10: cosmetics | B10: SKU8 | C10: 68.72 | D10: 78 | E10: 150 | F10: 7517.36 | G10: Female | H10: 5 | I10: 10 | J10: 15 | K10: 7 | L10: Carrier C | M10: 3.4 | N10: Supplier 4 | O10: Mumbai | P10: 13 | Q10: 769 | R10: 8 | S10: 11.42 | T10: Pending | U10: 2.71 | V10: Sea | W10: Route B | X10: 505.56 | Y10: 3.1400461 | Z10: normal | AA10: 51.889339 | AB10: 96.125 | AC10: 67.338004 | AD10: 520.38
A11: skincare | B11: SKU9 | C11: 64.02 | D11: 35 | E11: 980 | F11: 4971.15 | G11: Unknown | H11: 14 | I11: 27 | J11: 83 | K11: 1 | L11: Carrier A | M11: 7.17 | N11: Supplier 2 | O11: Chennai | P11: 29 | Q11: 963 | R11: 23 | S11: 47.96 | T11: Pending | U11: 3.84 | V11: Rail | W11: Route B | X11: 995.93 | Y11: 20.514968 | Z11: normal | AA11: 17.467803 | AB11: 41.869565 | AC11: 20.079233 | AD11: 1051.06
A12: skincare | B12: SKU10 | C12: 15.71 | D12: 11 | E12: 996 | F12: 2330.97 | G12: Non-binary | H12: 51 | I12: 13 | J12: 80 | K12: 2 | L12: Carrier C | M12: 8.67 | N12: Supplier 5 | O12: Kolkata | P12: 18 | Q12: 830 | R12: 5 | S12: 96.53 | T12: Pass | U12: 1.73 | V12: Road | W12: Route B | X12: 806.1 | Y12: 20.849906 | Z12: normal | AA12: 7.8897338 | AB12: 166 | AC12: 8.5983632 | AD12: 911.3
A13: skincare | B13: SKU11 | C13: 90.64 | D13: 95 | E13: 960 | F13: 6099.94 | G13: Female | H13: 46 | I13: 23 | J13: 60 | K13: 1 | L13: Carrier A | M13: 4.52 | N13: Supplier 2 | O13: Kolkata | P13: 28 | Q13: 362 | R13: 11 | S13: 27.59 | T13: Pending | U13: 0.02 | V13: Air | W13: Route A | X13: 126.72 | Y13: 20.096295 | Z13: normal | AA13: 11.273746 | AB13: 32.909091 | AC13: 13.120696 | AD13: 158.83
A14: haircare | B14: SKU12 | C14: 71.21 | D14: 41 | E14: 336 | F14: 2873.74 | G14: Unknown | H14: 100 | I14: 30 | J14: 85 | K14: 4 | L14: Carrier A | M14: 1.33 | N14: Supplier 4 | O14: Kolkata | P14: 3 | Q14: 563 | R14: 3 | S14: 32.32 | T14: Fail | U14: 2.16 | V14: Road | W14: Route B | X14: 402.97 | Y14: 7.0337032 | Z14: normal | AA14: 16.731055 | AB14: 187.66667 | AC14: 17.419554 | AD14: 436.62
... A101: haircare | B101: SKU99 | C101: 68.52 | D101: 17 | E101: 627 | F101: 9185.19 | G101: Unknown | H101: 55 | I101: 8 | J101: 59 | K101: 6 | L101: Carrier B | M101: 1.31 | N101: Supplier 2 | O101: Chennai | P101: 29 | Q101: 921 | R101: 2 | S101: 38.07 | T101: Fail | U101: 0.35 | V101: Rail | W101: Route B | X101: 210.74 | Y101: 13.125393 | Z101: normal | AA101: 23.387506 | AB101: 460.5 | AC101: 24.192277 | AD101: 250.12
L103: {=_xlfn.UNIQUE(supply_chain_data[Shipping carriers])} -> Carrier B | N103: {=_xlfn.UNIQUE(supply_chain_data[Supplier name])} -> Supplier 3 | O103: {=_xlfn.UNIQUE(supply_chain_data[Location])} -> Mumbai | T103: {=_xlfn.UNIQUE(supply_chain_data[Inspection results])} -> Pending | V103: {=_xlfn.UNIQUE(supply_chain_data[Transportation modes])} -> Road | W103: {=_xlfn.UNIQUE(supply_chain_data[Routes])} -> Route B
G104: {=_xlfn.UNIQUE(supply_chain_data[Customer demographics])} -> Non-binary | L104: Carrier A | N104: Supplier 1 | O104: Kolkata | T104: Fail | V104: Air | W104: Route C
A105: {=_xlfn.UNIQUE(supply_chain_data[Product type])} -> haircare | B105: {=_xlfn.UNIQUE(supply_chain_data[SKU])} -> SKU0 | G105: Female | L105: Carrier C | N105: Supplier 5 | O105: Delhi | T105: Pass | V105: Rail | W105: Route A
A106: skincare | B106: SKU1 | G106: Unknown | N106: Supplier 4 | O106: Bangalore | V106: Sea
A107: cosmetics | B107: SKU2 | G107: Male | N107: Supplier 2 | O107: Chennai
B108: SKU3
B109: SKU4
B110: SKU5
B111: SKU6
B112: SKU7
B113: SKU8
B114: SKU9
B115: SKU10
B116: SKU11
B117: SKU12
B118: SKU13
B119: SKU14
... B204: SKU99

Sheet Revenue vs. Lead Time by SKU

Sheet Shipping Costs and Times by Car

Sheet Total Cost vs. Defect Rates

Sheet Shipping and Lead Time Analysis

Sheet Business question
C2: Business Question
B3: 1 | C3: which product typyes generate the highest total revenue?
B4: 2 | C4: what are the top 10 SKUs by number of products sold?
B5: 3 | C5: which SKUs have high prices but low sales volume?
B6: 4 | C6: what is the average selling price per product type?
B7: 5 | C7: which product contribute the most to total revenue?
B8: 6 | C8: how many SKUs are currently out of stock?
B9: 7 | C9: which product are at risk of stockout based on current stock levels and sales?
B10: 8 | C10: what is the inventory turnover ratio for each SKU?
B11: 9 | C11: which products have excess inventory compared to their sales?
B12: 10 | C12: what is the reorder point for each SKU?
B13: 11 | C13: which customer segment generates the highest revenue?
B14: 12 | C14: how do sales volumes differ across customer demographics?
... B32: 30 | C32: id demand increases by 20% which parts of the supply chain will be most affected?

Sheet Descriptive statistics
F1: KPIs
F2: sales & revenue performace KPIs
A3: lead time | F3: total revenue generated | G3: =SUM(supply_chain_data[Revenue generated]) -> 577604.86 | H3: revenue contribution % | I3: =SUMIF(supply_chain_data[Product type],supply_chain!A2,supply_chain_data[Revenue generated]) / SUM(supply_chain_data[Revenue generated]) -> 0.30203247
A4: Average | B4: =AVERAGE(supply_chain_data[Lead time]) -> 17.08 | C4: coefficient of variation(cv) | D4: ='Descriptive statistics'!B4 / 'Descriptive statistics'!B5 -> 1.9538395 | F4: total number of product sold | G4: =SUM(supply_chain_data[Number of products sold]) -> 46099 | H4: customer segment revenue share | I4: =SUMIF(supply_chain_data[Customer demographics],supply_chain!G2,supply_chain_data[Revenue generated]) / SUM(supply_chain_data[Revenue generated]) -> 0.20146266
A5: standard devation | B5: =_xlfn.STDEV.P(supply_chain_data[Lead times]) -> 8.7417618 | C5: uniqe supplier name | D5: =COUNTA(_xlfn.UNIQUE(supply_chain_data[Supplier name])) -> 5 | F5: average selling price(ASP) | G5: =SUM(supply_chain_data[Number of products sold]) / SUM(supply_chain_data[Revenue generated]) -> 0.079810617
A6: range | B6: =MAX(supply_chain_data[Lead times])-MIN(supply_chain_data[Lead times]) -> 29 | F6: inventory & demand efficiency KPIs
A7: IQR | B7: =_xlfn.QUARTILE.INC(supply_chain_data[Lead time],3)-_xlfn.QUARTILE.INC(supply_chain_data[Lead time],1) -> 15 | F7: average stock levels | G7: =AVERAGE(supply_chain_data[Stock levels]) -> 47.77
A8: percentiles | B8: =_xlfn.PERCENTILE.INC(supply_chain_data[Lead times],0.9) -> 27 | F8: Slow-Moving Items % | G8: =COUNTIF(supply_chain!Y2:Y100,"<1")/COUNTA(supply_chain_data[SKU]) -> 0.05
A9: shipping costs | F9: Total Stok on Hand | G9: =SUM(supply_chain_data[Stock levels]) -> 4777
A10: first quartiles | B10: =_xlfn.QUARTILE.INC(supply_chain_data[Shipping costs],1) -> 3.5425 | C10: trimmed mean | D10: =TRIMMEAN(supply_chain_data[Shipping costs],0.1) -> 5.5551111 | F10: Inventory Turnover | G10: =SUM(supply_chain_data[Number of products sold]) / AVERAGE(supply_chain_data[Stock levels]) -> 965.01989
A11: third quartiles | B11: =_xlfn.QUARTILE.INC(supply_chain_data[Shipping costs],3) -> 7.6025 | C11: skewness | D11: =SKEW(supply_chain_data[Shipping costs]) -> -0.05379662
A12: TQR | B12: =B11-B10 -> 4.06 | C12: kurtosis | D12: =KURT(supply_chain_data[Lead time]) -> -1.1745173 | F12: Supplier & manufacturing performance
A13: lower | B13: =B10-1.5*B12 -> -2.5475 | F13: Average Supplier Lead Time | G13: =AVERAGEIF(supply_chain_data[Supplier name],supply_chain!N2,supply_chain_data[Lead time]) -> 20.133333
A14: upper | B14: =B11+1.5*B12 -> 13.6925 | F14: Supplier Costs Per Unit | G14: =SUM(supply_chain_data[Manufacturing costs]) / SUM(supply_chain_data[Production volumes]) -> 0.083238941
A15: correlation(lead time, shipping costs) | B15: =CORREL(supply_chain_data[Lead time],supply_chain_data[Shipping costs]) -> 0.029793588 | C15: percentage failing ispection | D15: =COUNTIF(supply_chain_data[Inspection results], "Fail") / COUNTA(supply_chain_data[Inspection results]) -> 0.36 | F15: Production Share By Supplier | G15: =SUMIF(supply_chain_data[Supplier name],supply_chain!N2,supply_chain_data[Production volumes]) / SUM(supply_chain_data[Production volumes]) -> 0.14083192
F16: On Time Performance | G16: =COUNTIF(supply_chain_data[Lead time], "<"&AVERAGE(supply_chain_data[Lead time])) / COUNT(supply_chain_data[Lead time]) -> 0.43
A17: median | B17: =MEDIAN(supply_chain_data[Shipping costs]) -> 5.32 | F17: Logistic & Transportation
A18: stock level | F18: Avrage Shipping Cost | G18: =AVERAGE(supply_chain_data[Shipping costs]) -> 5.5482
A19: min | B19: =MIN(supply_chain_data[Stock levels]) -> 0 | F19: Sipping Cost Per Unit | G19: =SUM(supply_chain_data[Shipping costs]) / SUM(supply_chain_data[Number of products sold]) -> 0.012035402
A20: max | B20: =MAX(supply_chain_data[Stock levels]) -> 100 | F20: Average Shipping Time | G20: =AVERAGE(supply_chain_data[Shipping times]) -> 5.75
A21: manufacturing costs | F21: Cost Per Transportation Mode | G21: =SUMIFS(supply_chain_data[Shipping costs],supply_chain_data[Transportation modes],supply_chain!V2) -> 160.73
A22: variance | B22: =_xlfn.VAR.P(supply_chain_data[Manufacturing costs]) -> 831.6014 | F22: Lead Time Variability | G22: =_xlfn.STDEV.P(supply_chain_data[Lead time]) -> 8.8019089
A23: ________________________________ | F23: Cost, Quality & Risk Analysis
A24: compare means by group (Supplier 5) | B24: =AVERAGEIFS(supply_chain_data[Lead time],supply_chain_data[Supplier name],supply_chain!N86) -> 18.055556 | F24: Total Cost | G24: =SUM(supply_chain_data[costs]) -> 52924.57
F25: Cost Per SKU | G25: =SUMIFS(supply_chain_data[costs],supply_chain_data[SKU],supply_chain!B2) -> 187.75
F26: Average Defect Rates | G26: =AVERAGE(supply_chain_data[Defect rates]) -> 2.2771
F27: Revenue at Risk (Due to Lead Time) | G27: =AVERAGEIFS(supply_chain_data[Revenue generated],supply_chain_data[Lead times],">"&AVERAGEA(supply_chain_data[Lead times])) -> 5593.8424
F28: Quality Pass Rate | G28: =COUNTIF(supply_chain_data[Inspection results],"Pass") / COUNTA(supply_chain_data[Inspection results]) -> 0.23

Sheet Sales & Revenue Performance

Sheet Inventory & Demand Efficiency

Sheet Supplier & manufacturing perfor

Sheet Logistic & Transportation

Sheet Cost, Quality & Risk Analysis 
